[{"arguments":["clang","-Wno-documentation-unknown-command","-Wno-unknown-warning-option","-Wno-unknown-pragmas","-nostdinc","-nostdinc++","-g","-std=gnu++1z","-Wall","-Wextra","-Wextra","-fexceptions","-mthreads","-fsyntax-only","-m64","--target=x86_64-w64-mingw32","-DUNICODE","-D_UNICODE","-DWIN32","-DMINGW_HAS_SECURE_API","-DQT_QML_DEBUG","-DQT_QUICKCONTROLS2_LIB","-DQT_QUICK_LIB","-DQT_OPENGL_LIB","-DQT_WIDGETS_LIB","-DQT_GUI_LIB","-DQT_QMLMODELS_LIB","-DQT_QML_LIB","-DQT_QMLINTEGRATION_LIB","-DQT_NETWORK_LIB","-DQT_CORE_LIB","-DQT_NEEDS_QMAIN","-DQ_CREATOR_RUN","-DQT_ANNOTATE_FUNCTION(x)=__attribute__((annotate(#x)))","-ID:\\pliki\\qt\\Tools\\Qt Creator 13.0.0-rc1\\share\\qtcreator\\cplusplus\\wrappedMingwHeaders","-ID:\\pliki\\qt\\Tools\\Qt Creator 13.0.0-rc1\\share\\qtcreator\\cplusplus\\wrappedQtHeaders","-ID:\\pliki\\qt\\Tools\\Qt Creator 13.0.0-rc1\\share\\qtcreator\\cplusplus\\wrappedQtHeaders\\QtCore","-ID:\\proejcts\\qtYTDownalde\\YtDownloaderQt","-ID:\\proejcts\\qtYTDownalde\\YtDownloaderQt\\YtDlpWrapper","-ID:\\pliki\\qt\\6.6.2\\mingw_64\\include","-ID:\\pliki\\qt\\6.6.2\\mingw_64\\include\\QtQuickControls2","-ID:\\pliki\\qt\\6.6.2\\mingw_64\\include\\QtQuick","-ID:\\pliki\\qt\\6.6.2\\mingw_64\\include\\QtOpenGL","-ID:\\pliki\\qt\\6.6.2\\mingw_64\\include\\QtWidgets","-ID:\\pliki\\qt\\6.6.2\\mingw_64\\include\\QtGui","-ID:\\pliki\\qt\\6.6.2\\mingw_64\\include\\QtQmlModels","-ID:\\pliki\\qt\\6.6.2\\mingw_64\\include\\QtQml","-ID:\\pliki\\qt\\6.6.2\\mingw_64\\include\\QtQmlIntegration","-ID:\\pliki\\qt\\6.6.2\\mingw_64\\include\\QtNetwork","-ID:\\pliki\\qt\\6.6.2\\mingw_64\\include\\QtCore","-ID:\\proejcts\\qtYTDownalde\\YtDownloaderQt\\build\\Desktop_Qt_6_6_2_MinGW_64_bit-Debug\\debug","-ID:\\proejcts\\qtYTDownalde\\YtDownloaderQt\\build\\Desktop_Qt_6_6_2_MinGW_64_bit-Debug","-ID:\\pliki\\qt\\6.6.2\\mingw_64\\mkspecs\\win32-g++","-isystem","D:\\pliki\\qt\\Tools\\mingw1120_64\\lib\\gcc\\x86_64-w64-mingw32\\11.2.0\\include\\c++","-isystem","D:\\pliki\\qt\\Tools\\mingw1120_64\\lib\\gcc\\x86_64-w64-mingw32\\11.2.0\\include\\c++\\x86_64-w64-mingw32","-isystem","D:\\pliki\\qt\\Tools\\mingw1120_64\\lib\\gcc\\x86_64-w64-mingw32\\11.2.0\\include\\c++\\backward","-isystem","D:\\pliki\\qt\\Tools\\Qt Creator 13.0.0-rc1\\bin\\clang\\lib\\clang\\17\\include","-isystem","D:\\pliki\\qt\\Tools\\mingw1120_64\\x86_64-w64-mingw32\\include","-fmessage-length=0","-fdiagnostics-show-note-include-stack","-fretain-comments-from-system-headers","-fmacro-backtrace-limit=0","-ferror-limit=1000","-x","c++","D:\\proejcts\\qtYTDownalde\\YtDownloaderQt\\Worker.cpp"],"directory":"D:/proejcts/qtYTDownalde/YtDownloaderQt/build/Desktop_Qt_6_6_2_MinGW_64_bit-Debug/.qtc_clangd","file":"D:/proejcts/qtYTDownalde/YtDownloaderQt/Worker.cpp"},{"arguments":["clang","-Wno-documentation-unknown-command","-Wno-unknown-warning-option","-Wno-unknown-pragmas","-nostdinc","-nostdinc++","-g","-std=gnu++1z","-Wall","-Wextra","-Wextra","-fexceptions","-mthreads","-fsyntax-only","-m64","--target=x86_64-w64-mingw32","-DUNICODE","-D_UNICODE","-DWIN32","-DMINGW_HAS_SECURE_API","-DQT_QML_DEBUG","-DQT_QUICKCONTROLS2_LIB","-DQT_QUICK_LIB","-DQT_OPENGL_LIB","-DQT_WIDGETS_LIB","-DQT_GUI_LIB","-DQT_QMLMODELS_LIB","-DQT_QML_LIB","-DQT_QMLINTEGRATION_LIB","-DQT_NETWORK_LIB","-DQT_CORE_LIB","-DQT_NEEDS_QMAIN","-DQ_CREATOR_RUN","-DQT_ANNOTATE_FUNCTION(x)=__attribute__((annotate(#x)))","-ID:\\pliki\\qt\\Tools\\Qt Creator 13.0.0-rc1\\share\\qtcreator\\cplusplus\\wrappedMingwHeaders","-ID:\\pliki\\qt\\Tools\\Qt Creator 13.0.0-rc1\\share\\qtcreator\\cplusplus\\wrappedQtHeaders","-ID:\\pliki\\qt\\Tools\\Qt Creator 13.0.0-rc1\\share\\qtcreator\\cplusplus\\wrappedQtHeaders\\QtCore","-ID:\\proejcts\\qtYTDownalde\\YtDownloaderQt","-ID:\\proejcts\\qtYTDownalde\\YtDownloaderQt\\YtDlpWrapper","-ID:\\pliki\\qt\\6.6.2\\mingw_64\\include","-ID:\\pliki\\qt\\6.6.2\\mingw_64\\include\\QtQuickControls2","-ID:\\pliki\\qt\\6.6.2\\mingw_64\\include\\QtQuick","-ID:\\pliki\\qt\\6.6.2\\mingw_64\\include\\QtOpenGL","-ID:\\pliki\\qt\\6.6.2\\mingw_64\\include\\QtWidgets","-ID:\\pliki\\qt\\6.6.2\\mingw_64\\include\\QtGui","-ID:\\pliki\\qt\\6.6.2\\mingw_64\\include\\QtQmlModels","-ID:\\pliki\\qt\\6.6.2\\mingw_64\\include\\QtQml","-ID:\\pliki\\qt\\6.6.2\\mingw_64\\include\\QtQmlIntegration","-ID:\\pliki\\qt\\6.6.2\\mingw_64\\include\\QtNetwork","-ID:\\pliki\\qt\\6.6.2\\mingw_64\\include\\QtCore","-ID:\\proejcts\\qtYTDownalde\\YtDownloaderQt\\build\\Desktop_Qt_6_6_2_MinGW_64_bit-Debug\\debug","-ID:\\proejcts\\qtYTDownalde\\YtDownloaderQt\\build\\Desktop_Qt_6_6_2_MinGW_64_bit-Debug","-ID:\\pliki\\qt\\6.6.2\\mingw_64\\mkspecs\\win32-g++","-isystem","D:\\pliki\\qt\\Tools\\mingw1120_64\\lib\\gcc\\x86_64-w64-mingw32\\11.2.0\\include\\c++","-isystem","D:\\pliki\\qt\\Tools\\mingw1120_64\\lib\\gcc\\x86_64-w64-mingw32\\11.2.0\\include\\c++\\x86_64-w64-mingw32","-isystem","D:\\pliki\\qt\\Tools\\mingw1120_64\\lib\\gcc\\x86_64-w64-mingw32\\11.2.0\\include\\c++\\backward","-isystem","D:\\pliki\\qt\\Tools\\Qt Creator 13.0.0-rc1\\bin\\clang\\lib\\clang\\17\\include","-isystem","D:\\pliki\\qt\\Tools\\mingw1120_64\\x86_64-w64-mingw32\\include","-fmessage-length=0","-fdiagnostics-show-note-include-stack","-fretain-comments-from-system-headers","-fmacro-backtrace-limit=0","-ferror-limit=1000","-x","c++","D:\\proejcts\\qtYTDownalde\\YtDownloaderQt\\main.cpp"],"directory":"D:/proejcts/qtYTDownalde/YtDownloaderQt/build/Desktop_Qt_6_6_2_MinGW_64_bit-Debug/.qtc_clangd","file":"D:/proejcts/qtYTDownalde/YtDownloaderQt/main.cpp"},{"arguments":["clang","-Wno-documentation-unknown-command","-Wno-unknown-warning-option","-Wno-unknown-pragmas","-nostdinc","-nostdinc++","-g","-std=gnu++1z","-Wall","-Wextra","-Wextra","-fexceptions","-mthreads","-fsyntax-only","-m64","--target=x86_64-w64-mingw32","-DUNICODE","-D_UNICODE","-DWIN32","-DMINGW_HAS_SECURE_API","-DQT_QML_DEBUG","-DQT_QUICKCONTROLS2_LIB","-DQT_QUICK_LIB","-DQT_OPENGL_LIB","-DQT_WIDGETS_LIB","-DQT_GUI_LIB","-DQT_QMLMODELS_LIB","-DQT_QML_LIB","-DQT_QMLINTEGRATION_LIB","-DQT_NETWORK_LIB","-DQT_CORE_LIB","-DQT_NEEDS_QMAIN","-DQ_CREATOR_RUN","-DQT_ANNOTATE_FUNCTION(x)=__attribute__((annotate(#x)))","-ID:\\pliki\\qt\\Tools\\Qt Creator 13.0.0-rc1\\share\\qtcreator\\cplusplus\\wrappedMingwHeaders","-ID:\\pliki\\qt\\Tools\\Qt Creator 13.0.0-rc1\\share\\qtcreator\\cplusplus\\wrappedQtHeaders","-ID:\\pliki\\qt\\Tools\\Qt Creator 13.0.0-rc1\\share\\qtcreator\\cplusplus\\wrappedQtHeaders\\QtCore","-ID:\\proejcts\\qtYTDownalde\\YtDownloaderQt","-ID:\\proejcts\\qtYTDownalde\\YtDownloaderQt\\YtDlpWrapper","-ID:\\pliki\\qt\\6.6.2\\mingw_64\\include","-ID:\\pliki\\qt\\6.6.2\\mingw_64\\include\\QtQuickControls2","-ID:\\pliki\\qt\\6.6.2\\mingw_64\\include\\QtQuick","-ID:\\pliki\\qt\\6.6.2\\mingw_64\\include\\QtOpenGL","-ID:\\pliki\\qt\\6.6.2\\mingw_64\\include\\QtWidgets","-ID:\\pliki\\qt\\6.6.2\\mingw_64\\include\\QtGui","-ID:\\pliki\\qt\\6.6.2\\mingw_64\\include\\QtQmlModels","-ID:\\pliki\\qt\\6.6.2\\mingw_64\\include\\QtQml","-ID:\\pliki\\qt\\6.6.2\\mingw_64\\include\\QtQmlIntegration","-ID:\\pliki\\qt\\6.6.2\\mingw_64\\include\\QtNetwork","-ID:\\pliki\\qt\\6.6.2\\mingw_64\\include\\QtCore","-ID:\\proejcts\\qtYTDownalde\\YtDownloaderQt\\build\\Desktop_Qt_6_6_2_MinGW_64_bit-Debug\\debug","-ID:\\proejcts\\qtYTDownalde\\YtDownloaderQt\\build\\Desktop_Qt_6_6_2_MinGW_64_bit-Debug","-ID:\\pliki\\qt\\6.6.2\\mingw_64\\mkspecs\\win32-g++","-isystem","D:\\pliki\\qt\\Tools\\mingw1120_64\\lib\\gcc\\x86_64-w64-mingw32\\11.2.0\\include\\c++","-isystem","D:\\pliki\\qt\\Tools\\mingw1120_64\\lib\\gcc\\x86_64-w64-mingw32\\11.2.0\\include\\c++\\x86_64-w64-mingw32","-isystem","D:\\pliki\\qt\\Tools\\mingw1120_64\\lib\\gcc\\x86_64-w64-mingw32\\11.2.0\\include\\c++\\backward","-isystem","D:\\pliki\\qt\\Tools\\Qt Creator 13.0.0-rc1\\bin\\clang\\lib\\clang\\17\\include","-isystem","D:\\pliki\\qt\\Tools\\mingw1120_64\\x86_64-w64-mingw32\\include","-fmessage-length=0","-fdiagnostics-show-note-include-stack","-fretain-comments-from-system-headers","-fmacro-backtrace-limit=0","-ferror-limit=1000","-x","c++","D:\\proejcts\\qtYTDownalde\\YtDownloaderQt\\videolistelement.cpp"],"directory":"D:/proejcts/qtYTDownalde/YtDownloaderQt/build/Desktop_Qt_6_6_2_MinGW_64_bit-Debug/.qtc_clangd","file":"D:/proejcts/qtYTDownalde/YtDownloaderQt/videolistelement.cpp"},{"arguments":["clang","-Wno-documentation-unknown-command","-Wno-unknown-warning-option","-Wno-unknown-pragmas","-nostdinc","-nostdinc++","-g","-std=gnu++1z","-Wall","-Wextra","-Wextra","-fexceptions","-mthreads","-fsyntax-only","-m64","--target=x86_64-w64-mingw32","-DUNICODE","-D_UNICODE","-DWIN32","-DMINGW_HAS_SECURE_API","-DQT_QML_DEBUG","-DQT_QUICKCONTROLS2_LIB","-DQT_QUICK_LIB","-DQT_OPENGL_LIB","-DQT_WIDGETS_LIB","-DQT_GUI_LIB","-DQT_QMLMODELS_LIB","-DQT_QML_LIB","-DQT_QMLINTEGRATION_LIB","-DQT_NETWORK_LIB","-DQT_CORE_LIB","-DQT_NEEDS_QMAIN","-DQ_CREATOR_RUN","-DQT_ANNOTATE_FUNCTION(x)=__attribute__((annotate(#x)))","-ID:\\pliki\\qt\\Tools\\Qt Creator 13.0.0-rc1\\share\\qtcreator\\cplusplus\\wrappedMingwHeaders","-ID:\\pliki\\qt\\Tools\\Qt Creator 13.0.0-rc1\\share\\qtcreator\\cplusplus\\wrappedQtHeaders","-ID:\\pliki\\qt\\Tools\\Qt Creator 13.0.0-rc1\\share\\qtcreator\\cplusplus\\wrappedQtHeaders\\QtCore","-ID:\\proejcts\\qtYTDownalde\\YtDownloaderQt","-ID:\\proejcts\\qtYTDownalde\\YtDownloaderQt\\YtDlpWrapper","-ID:\\pliki\\qt\\6.6.2\\mingw_64\\include","-ID:\\pliki\\qt\\6.6.2\\mingw_64\\include\\QtQuickControls2","-ID:\\pliki\\qt\\6.6.2\\mingw_64\\include\\QtQuick","-ID:\\pliki\\qt\\6.6.2\\mingw_64\\include\\QtOpenGL","-ID:\\pliki\\qt\\6.6.2\\mingw_64\\include\\QtWidgets","-ID:\\pliki\\qt\\6.6.2\\mingw_64\\include\\QtGui","-ID:\\pliki\\qt\\6.6.2\\mingw_64\\include\\QtQmlModels","-ID:\\pliki\\qt\\6.6.2\\mingw_64\\include\\QtQml","-ID:\\pliki\\qt\\6.6.2\\mingw_64\\include\\QtQmlIntegration","-ID:\\pliki\\qt\\6.6.2\\mingw_64\\include\\QtNetwork","-ID:\\pliki\\qt\\6.6.2\\mingw_64\\include\\QtCore","-ID:\\proejcts\\qtYTDownalde\\YtDownloaderQt\\build\\Desktop_Qt_6_6_2_MinGW_64_bit-Debug\\debug","-ID:\\proejcts\\qtYTDownalde\\YtDownloaderQt\\build\\Desktop_Qt_6_6_2_MinGW_64_bit-Debug","-ID:\\pliki\\qt\\6.6.2\\mingw_64\\mkspecs\\win32-g++","-isystem","D:\\pliki\\qt\\Tools\\mingw1120_64\\lib\\gcc\\x86_64-w64-mingw32\\11.2.0\\include\\c++","-isystem","D:\\pliki\\qt\\Tools\\mingw1120_64\\lib\\gcc\\x86_64-w64-mingw32\\11.2.0\\include\\c++\\x86_64-w64-mingw32","-isystem","D:\\pliki\\qt\\Tools\\mingw1120_64\\lib\\gcc\\x86_64-w64-mingw32\\11.2.0\\include\\c++\\backward","-isystem","D:\\pliki\\qt\\Tools\\Qt Creator 13.0.0-rc1\\bin\\clang\\lib\\clang\\17\\include","-isystem","D:\\pliki\\qt\\Tools\\mingw1120_64\\x86_64-w64-mingw32\\include","-fmessage-length=0","-fdiagnostics-show-note-include-stack","-fretain-comments-from-system-headers","-fmacro-backtrace-limit=0","-ferror-limit=1000","-x","c++","D:\\proejcts\\qtYTDownalde\\YtDownloaderQt\\ytdownloader.cpp"],"directory":"D:/proejcts/qtYTDownalde/YtDownloaderQt/build/Desktop_Qt_6_6_2_MinGW_64_bit-Debug/.qtc_clangd","file":"D:/proejcts/qtYTDownalde/YtDownloaderQt/ytdownloader.cpp"},{"arguments":["clang","-Wno-documentation-unknown-command","-Wno-unknown-warning-option","-Wno-unknown-pragmas","-nostdinc","-nostdinc++","-g","-std=gnu++1z","-Wall","-Wextra","-Wextra","-fexceptions","-mthreads","-fsyntax-only","-m64","--target=x86_64-w64-mingw32","-DUNICODE","-D_UNICODE","-DWIN32","-DMINGW_HAS_SECURE_API","-DQT_QML_DEBUG","-DQT_QUICKCONTROLS2_LIB","-DQT_QUICK_LIB","-DQT_OPENGL_LIB","-DQT_WIDGETS_LIB","-DQT_GUI_LIB","-DQT_QMLMODELS_LIB","-DQT_QML_LIB","-DQT_QMLINTEGRATION_LIB","-DQT_NETWORK_LIB","-DQT_CORE_LIB","-DQT_NEEDS_QMAIN","-DQ_CREATOR_RUN","-DQT_ANNOTATE_FUNCTION(x)=__attribute__((annotate(#x)))","-ID:\\pliki\\qt\\Tools\\Qt Creator 13.0.0-rc1\\share\\qtcreator\\cplusplus\\wrappedMingwHeaders","-ID:\\pliki\\qt\\Tools\\Qt Creator 13.0.0-rc1\\share\\qtcreator\\cplusplus\\wrappedQtHeaders","-ID:\\pliki\\qt\\Tools\\Qt Creator 13.0.0-rc1\\share\\qtcreator\\cplusplus\\wrappedQtHeaders\\QtCore","-ID:\\proejcts\\qtYTDownalde\\YtDownloaderQt","-ID:\\proejcts\\qtYTDownalde\\YtDownloaderQt\\YtDlpWrapper","-ID:\\pliki\\qt\\6.6.2\\mingw_64\\include","-ID:\\pliki\\qt\\6.6.2\\mingw_64\\include\\QtQuickControls2","-ID:\\pliki\\qt\\6.6.2\\mingw_64\\include\\QtQuick","-ID:\\pliki\\qt\\6.6.2\\mingw_64\\include\\QtOpenGL","-ID:\\pliki\\qt\\6.6.2\\mingw_64\\include\\QtWidgets","-ID:\\pliki\\qt\\6.6.2\\mingw_64\\include\\QtGui","-ID:\\pliki\\qt\\6.6.2\\mingw_64\\include\\QtQmlModels","-ID:\\pliki\\qt\\6.6.2\\mingw_64\\include\\QtQml","-ID:\\pliki\\qt\\6.6.2\\mingw_64\\include\\QtQmlIntegration","-ID:\\pliki\\qt\\6.6.2\\mingw_64\\include\\QtNetwork","-ID:\\pliki\\qt\\6.6.2\\mingw_64\\include\\QtCore","-ID:\\proejcts\\qtYTDownalde\\YtDownloaderQt\\build\\Desktop_Qt_6_6_2_MinGW_64_bit-Debug\\debug","-ID:\\proejcts\\qtYTDownalde\\YtDownloaderQt\\build\\Desktop_Qt_6_6_2_MinGW_64_bit-Debug","-ID:\\pliki\\qt\\6.6.2\\mingw_64\\mkspecs\\win32-g++","-isystem","D:\\pliki\\qt\\Tools\\mingw1120_64\\lib\\gcc\\x86_64-w64-mingw32\\11.2.0\\include\\c++","-isystem","D:\\pliki\\qt\\Tools\\mingw1120_64\\lib\\gcc\\x86_64-w64-mingw32\\11.2.0\\include\\c++\\x86_64-w64-mingw32","-isystem","D:\\pliki\\qt\\Tools\\mingw1120_64\\lib\\gcc\\x86_64-w64-mingw32\\11.2.0\\include\\c++\\backward","-isystem","D:\\pliki\\qt\\Tools\\Qt Creator 13.0.0-rc1\\bin\\clang\\lib\\clang\\17\\include","-isystem","D:\\pliki\\qt\\Tools\\mingw1120_64\\x86_64-w64-mingw32\\include","-fmessage-length=0","-fdiagnostics-show-note-include-stack","-fretain-comments-from-system-headers","-fmacro-backtrace-limit=0","-ferror-limit=1000","-x","c++","D:\\proejcts\\qtYTDownalde\\YtDownloaderQt\\YtDlpWrapper\\YoutubeDownloader.cpp"],"directory":"D:/proejcts/qtYTDownalde/YtDownloaderQt/build/Desktop_Qt_6_6_2_MinGW_64_bit-Debug/.qtc_clangd","file":"D:/proejcts/qtYTDownalde/YtDownloaderQt/YtDlpWrapper/YoutubeDownloader.cpp"},{"arguments":["clang","-Wno-documentation-unknown-command","-Wno-unknown-warning-option","-Wno-unknown-pragmas","-nostdinc","-nostdinc++","-g","-std=gnu++1z","-Wall","-Wextra","-Wextra","-fexceptions","-mthreads","-fsyntax-only","-m64","--target=x86_64-w64-mingw32","-DUNICODE","-D_UNICODE","-DWIN32","-DMINGW_HAS_SECURE_API","-DQT_QML_DEBUG","-DQT_QUICKCONTROLS2_LIB","-DQT_QUICK_LIB","-DQT_OPENGL_LIB","-DQT_WIDGETS_LIB","-DQT_GUI_LIB","-DQT_QMLMODELS_LIB","-DQT_QML_LIB","-DQT_QMLINTEGRATION_LIB","-DQT_NETWORK_LIB","-DQT_CORE_LIB","-DQT_NEEDS_QMAIN","-DQ_CREATOR_RUN","-DQT_ANNOTATE_FUNCTION(x)=__attribute__((annotate(#x)))","-ID:\\pliki\\qt\\Tools\\Qt Creator 13.0.0-rc1\\share\\qtcreator\\cplusplus\\wrappedMingwHeaders","-ID:\\pliki\\qt\\Tools\\Qt Creator 13.0.0-rc1\\share\\qtcreator\\cplusplus\\wrappedQtHeaders","-ID:\\pliki\\qt\\Tools\\Qt Creator 13.0.0-rc1\\share\\qtcreator\\cplusplus\\wrappedQtHeaders\\QtCore","-ID:\\proejcts\\qtYTDownalde\\YtDownloaderQt","-ID:\\proejcts\\qtYTDownalde\\YtDownloaderQt\\YtDlpWrapper","-ID:\\pliki\\qt\\6.6.2\\mingw_64\\include","-ID:\\pliki\\qt\\6.6.2\\mingw_64\\include\\QtQuickControls2","-ID:\\pliki\\qt\\6.6.2\\mingw_64\\include\\QtQuick","-ID:\\pliki\\qt\\6.6.2\\mingw_64\\include\\QtOpenGL","-ID:\\pliki\\qt\\6.6.2\\mingw_64\\include\\QtWidgets","-ID:\\pliki\\qt\\6.6.2\\mingw_64\\include\\QtGui","-ID:\\pliki\\qt\\6.6.2\\mingw_64\\include\\QtQmlModels","-ID:\\pliki\\qt\\6.6.2\\mingw_64\\include\\QtQml","-ID:\\pliki\\qt\\6.6.2\\mingw_64\\include\\QtQmlIntegration","-ID:\\pliki\\qt\\6.6.2\\mingw_64\\include\\QtNetwork","-ID:\\pliki\\qt\\6.6.2\\mingw_64\\include\\QtCore","-ID:\\proejcts\\qtYTDownalde\\YtDownloaderQt\\build\\Desktop_Qt_6_6_2_MinGW_64_bit-Debug\\debug","-ID:\\proejcts\\qtYTDownalde\\YtDownloaderQt\\build\\Desktop_Qt_6_6_2_MinGW_64_bit-Debug","-ID:\\pliki\\qt\\6.6.2\\mingw_64\\mkspecs\\win32-g++","-isystem","D:\\pliki\\qt\\Tools\\mingw1120_64\\lib\\gcc\\x86_64-w64-mingw32\\11.2.0\\include\\c++","-isystem","D:\\pliki\\qt\\Tools\\mingw1120_64\\lib\\gcc\\x86_64-w64-mingw32\\11.2.0\\include\\c++\\x86_64-w64-mingw32","-isystem","D:\\pliki\\qt\\Tools\\mingw1120_64\\lib\\gcc\\x86_64-w64-mingw32\\11.2.0\\include\\c++\\backward","-isystem","D:\\pliki\\qt\\Tools\\Qt Creator 13.0.0-rc1\\bin\\clang\\lib\\clang\\17\\include","-isystem","D:\\pliki\\qt\\Tools\\mingw1120_64\\x86_64-w64-mingw32\\include","-fmessage-length=0","-fdiagnostics-show-note-include-stack","-fretain-comments-from-system-headers","-fmacro-backtrace-limit=0","-ferror-limit=1000","-x","c++","D:\\proejcts\\qtYTDownalde\\YtDownloaderQt\\YtDlpWrapper\\Executor.cpp"],"directory":"D:/proejcts/qtYTDownalde/YtDownloaderQt/build/Desktop_Qt_6_6_2_MinGW_64_bit-Debug/.qtc_clangd","file":"D:/proejcts/qtYTDownalde/YtDownloaderQt/YtDlpWrapper/Executor.cpp"},{"arguments":["clang","-Wno-documentation-unknown-command","-Wno-unknown-warning-option","-Wno-unknown-pragmas","-nostdinc","-nostdinc++","-g","-std=gnu++1z","-Wall","-Wextra","-Wextra","-fexceptions","-mthreads","-fsyntax-only","-m64","--target=x86_64-w64-mingw32","-DUNICODE","-D_UNICODE","-DWIN32","-DMINGW_HAS_SECURE_API","-DQT_QML_DEBUG","-DQT_QUICKCONTROLS2_LIB","-DQT_QUICK_LIB","-DQT_OPENGL_LIB","-DQT_WIDGETS_LIB","-DQT_GUI_LIB","-DQT_QMLMODELS_LIB","-DQT_QML_LIB","-DQT_QMLINTEGRATION_LIB","-DQT_NETWORK_LIB","-DQT_CORE_LIB","-DQT_NEEDS_QMAIN","-DQ_CREATOR_RUN","-DQT_ANNOTATE_FUNCTION(x)=__attribute__((annotate(#x)))","-ID:\\pliki\\qt\\Tools\\Qt Creator 13.0.0-rc1\\share\\qtcreator\\cplusplus\\wrappedMingwHeaders","-ID:\\pliki\\qt\\Tools\\Qt Creator 13.0.0-rc1\\share\\qtcreator\\cplusplus\\wrappedQtHeaders","-ID:\\pliki\\qt\\Tools\\Qt Creator 13.0.0-rc1\\share\\qtcreator\\cplusplus\\wrappedQtHeaders\\QtCore","-ID:\\proejcts\\qtYTDownalde\\YtDownloaderQt","-ID:\\proejcts\\qtYTDownalde\\YtDownloaderQt\\YtDlpWrapper","-ID:\\pliki\\qt\\6.6.2\\mingw_64\\include","-ID:\\pliki\\qt\\6.6.2\\mingw_64\\include\\QtQuickControls2","-ID:\\pliki\\qt\\6.6.2\\mingw_64\\include\\QtQuick","-ID:\\pliki\\qt\\6.6.2\\mingw_64\\include\\QtOpenGL","-ID:\\pliki\\qt\\6.6.2\\mingw_64\\include\\QtWidgets","-ID:\\pliki\\qt\\6.6.2\\mingw_64\\include\\QtGui","-ID:\\pliki\\qt\\6.6.2\\mingw_64\\include\\QtQmlModels","-ID:\\pliki\\qt\\6.6.2\\mingw_64\\include\\QtQml","-ID:\\pliki\\qt\\6.6.2\\mingw_64\\include\\QtQmlIntegration","-ID:\\pliki\\qt\\6.6.2\\mingw_64\\include\\QtNetwork","-ID:\\pliki\\qt\\6.6.2\\mingw_64\\include\\QtCore","-ID:\\proejcts\\qtYTDownalde\\YtDownloaderQt\\build\\Desktop_Qt_6_6_2_MinGW_64_bit-Debug\\debug","-ID:\\proejcts\\qtYTDownalde\\YtDownloaderQt\\build\\Desktop_Qt_6_6_2_MinGW_64_bit-Debug","-ID:\\pliki\\qt\\6.6.2\\mingw_64\\mkspecs\\win32-g++","-isystem","D:\\pliki\\qt\\Tools\\mingw1120_64\\lib\\gcc\\x86_64-w64-mingw32\\11.2.0\\include\\c++","-isystem","D:\\pliki\\qt\\Tools\\mingw1120_64\\lib\\gcc\\x86_64-w64-mingw32\\11.2.0\\include\\c++\\x86_64-w64-mingw32","-isystem","D:\\pliki\\qt\\Tools\\mingw1120_64\\lib\\gcc\\x86_64-w64-mingw32\\11.2.0\\include\\c++\\backward","-isystem","D:\\pliki\\qt\\Tools\\Qt Creator 13.0.0-rc1\\bin\\clang\\lib\\clang\\17\\include","-isystem","D:\\pliki\\qt\\Tools\\mingw1120_64\\x86_64-w64-mingw32\\include","-fmessage-length=0","-fdiagnostics-show-note-include-stack","-fretain-comments-from-system-headers","-fmacro-backtrace-limit=0","-ferror-limit=1000","-x","c++","D:\\proejcts\\qtYTDownalde\\YtDownloaderQt\\YtDlpWrapper\\Logger.cpp"],"directory":"D:/proejcts/qtYTDownalde/YtDownloaderQt/build/Desktop_Qt_6_6_2_MinGW_64_bit-Debug/.qtc_clangd","file":"D:/proejcts/qtYTDownalde/YtDownloaderQt/YtDlpWrapper/Logger.cpp"},{"arguments":["clang","-Wno-documentation-unknown-command","-Wno-unknown-warning-option","-Wno-unknown-pragmas","-nostdinc","-nostdinc++","-g","-std=gnu++1z","-Wall","-Wextra","-Wextra","-fexceptions","-mthreads","-fsyntax-only","-m64","--target=x86_64-w64-mingw32","-DUNICODE","-D_UNICODE","-DWIN32","-DMINGW_HAS_SECURE_API","-DQT_QML_DEBUG","-DQT_QUICKCONTROLS2_LIB","-DQT_QUICK_LIB","-DQT_OPENGL_LIB","-DQT_WIDGETS_LIB","-DQT_GUI_LIB","-DQT_QMLMODELS_LIB","-DQT_QML_LIB","-DQT_QMLINTEGRATION_LIB","-DQT_NETWORK_LIB","-DQT_CORE_LIB","-DQT_NEEDS_QMAIN","-DQ_CREATOR_RUN","-DQT_ANNOTATE_FUNCTION(x)=__attribute__((annotate(#x)))","-ID:\\pliki\\qt\\Tools\\Qt Creator 13.0.0-rc1\\share\\qtcreator\\cplusplus\\wrappedMingwHeaders","-ID:\\pliki\\qt\\Tools\\Qt Creator 13.0.0-rc1\\share\\qtcreator\\cplusplus\\wrappedQtHeaders","-ID:\\pliki\\qt\\Tools\\Qt Creator 13.0.0-rc1\\share\\qtcreator\\cplusplus\\wrappedQtHeaders\\QtCore","-ID:\\proejcts\\qtYTDownalde\\YtDownloaderQt","-ID:\\proejcts\\qtYTDownalde\\YtDownloaderQt\\YtDlpWrapper","-ID:\\pliki\\qt\\6.6.2\\mingw_64\\include","-ID:\\pliki\\qt\\6.6.2\\mingw_64\\include\\QtQuickControls2","-ID:\\pliki\\qt\\6.6.2\\mingw_64\\include\\QtQuick","-ID:\\pliki\\qt\\6.6.2\\mingw_64\\include\\QtOpenGL","-ID:\\pliki\\qt\\6.6.2\\mingw_64\\include\\QtWidgets","-ID:\\pliki\\qt\\6.6.2\\mingw_64\\include\\QtGui","-ID:\\pliki\\qt\\6.6.2\\mingw_64\\include\\QtQmlModels","-ID:\\pliki\\qt\\6.6.2\\mingw_64\\include\\QtQml","-ID:\\pliki\\qt\\6.6.2\\mingw_64\\include\\QtQmlIntegration","-ID:\\pliki\\qt\\6.6.2\\mingw_64\\include\\QtNetwork","-ID:\\pliki\\qt\\6.6.2\\mingw_64\\include\\QtCore","-ID:\\proejcts\\qtYTDownalde\\YtDownloaderQt\\build\\Desktop_Qt_6_6_2_MinGW_64_bit-Debug\\debug","-ID:\\proejcts\\qtYTDownalde\\YtDownloaderQt\\build\\Desktop_Qt_6_6_2_MinGW_64_bit-Debug","-ID:\\pliki\\qt\\6.6.2\\mingw_64\\mkspecs\\win32-g++","-isystem","D:\\pliki\\qt\\Tools\\mingw1120_64\\lib\\gcc\\x86_64-w64-mingw32\\11.2.0\\include\\c++","-isystem","D:\\pliki\\qt\\Tools\\mingw1120_64\\lib\\gcc\\x86_64-w64-mingw32\\11.2.0\\include\\c++\\x86_64-w64-mingw32","-isystem","D:\\pliki\\qt\\Tools\\mingw1120_64\\lib\\gcc\\x86_64-w64-mingw32\\11.2.0\\include\\c++\\backward","-isystem","D:\\pliki\\qt\\Tools\\Qt Creator 13.0.0-rc1\\bin\\clang\\lib\\clang\\17\\include","-isystem","D:\\pliki\\qt\\Tools\\mingw1120_64\\x86_64-w64-mingw32\\include","-fmessage-length=0","-fdiagnostics-show-note-include-stack","-fretain-comments-from-system-headers","-fmacro-backtrace-limit=0","-ferror-limit=1000","-x","c++-header","D:\\proejcts\\qtYTDownalde\\YtDownloaderQt\\Worker.h"],"directory":"D:/proejcts/qtYTDownalde/YtDownloaderQt/build/Desktop_Qt_6_6_2_MinGW_64_bit-Debug/.qtc_clangd","file":"D:/proejcts/qtYTDownalde/YtDownloaderQt/Worker.h"},{"arguments":["clang","-Wno-documentation-unknown-command","-Wno-unknown-warning-option","-Wno-unknown-pragmas","-nostdinc","-nostdinc++","-g","-std=gnu++1z","-Wall","-Wextra","-Wextra","-fexceptions","-mthreads","-fsyntax-only","-m64","--target=x86_64-w64-mingw32","-DUNICODE","-D_UNICODE","-DWIN32","-DMINGW_HAS_SECURE_API","-DQT_QML_DEBUG","-DQT_QUICKCONTROLS2_LIB","-DQT_QUICK_LIB","-DQT_OPENGL_LIB","-DQT_WIDGETS_LIB","-DQT_GUI_LIB","-DQT_QMLMODELS_LIB","-DQT_QML_LIB","-DQT_QMLINTEGRATION_LIB","-DQT_NETWORK_LIB","-DQT_CORE_LIB","-DQT_NEEDS_QMAIN","-DQ_CREATOR_RUN","-DQT_ANNOTATE_FUNCTION(x)=__attribute__((annotate(#x)))","-ID:\\pliki\\qt\\Tools\\Qt Creator 13.0.0-rc1\\share\\qtcreator\\cplusplus\\wrappedMingwHeaders","-ID:\\pliki\\qt\\Tools\\Qt Creator 13.0.0-rc1\\share\\qtcreator\\cplusplus\\wrappedQtHeaders","-ID:\\pliki\\qt\\Tools\\Qt Creator 13.0.0-rc1\\share\\qtcreator\\cplusplus\\wrappedQtHeaders\\QtCore","-ID:\\proejcts\\qtYTDownalde\\YtDownloaderQt","-ID:\\proejcts\\qtYTDownalde\\YtDownloaderQt\\YtDlpWrapper","-ID:\\pliki\\qt\\6.6.2\\mingw_64\\include","-ID:\\pliki\\qt\\6.6.2\\mingw_64\\include\\QtQuickControls2","-ID:\\pliki\\qt\\6.6.2\\mingw_64\\include\\QtQuick","-ID:\\pliki\\qt\\6.6.2\\mingw_64\\include\\QtOpenGL","-ID:\\pliki\\qt\\6.6.2\\mingw_64\\include\\QtWidgets","-ID:\\pliki\\qt\\6.6.2\\mingw_64\\include\\QtGui","-ID:\\pliki\\qt\\6.6.2\\mingw_64\\include\\QtQmlModels","-ID:\\pliki\\qt\\6.6.2\\mingw_64\\include\\QtQml","-ID:\\pliki\\qt\\6.6.2\\mingw_64\\include\\QtQmlIntegration","-ID:\\pliki\\qt\\6.6.2\\mingw_64\\include\\QtNetwork","-ID:\\pliki\\qt\\6.6.2\\mingw_64\\include\\QtCore","-ID:\\proejcts\\qtYTDownalde\\YtDownloaderQt\\build\\Desktop_Qt_6_6_2_MinGW_64_bit-Debug\\debug","-ID:\\proejcts\\qtYTDownalde\\YtDownloaderQt\\build\\Desktop_Qt_6_6_2_MinGW_64_bit-Debug","-ID:\\pliki\\qt\\6.6.2\\mingw_64\\mkspecs\\win32-g++","-isystem","D:\\pliki\\qt\\Tools\\mingw1120_64\\lib\\gcc\\x86_64-w64-mingw32\\11.2.0\\include\\c++","-isystem","D:\\pliki\\qt\\Tools\\mingw1120_64\\lib\\gcc\\x86_64-w64-mingw32\\11.2.0\\include\\c++\\x86_64-w64-mingw32","-isystem","D:\\pliki\\qt\\Tools\\mingw1120_64\\lib\\gcc\\x86_64-w64-mingw32\\11.2.0\\include\\c++\\backward","-isystem","D:\\pliki\\qt\\Tools\\Qt Creator 13.0.0-rc1\\bin\\clang\\lib\\clang\\17\\include","-isystem","D:\\pliki\\qt\\Tools\\mingw1120_64\\x86_64-w64-mingw32\\include","-fmessage-length=0","-fdiagnostics-show-note-include-stack","-fretain-comments-from-system-headers","-fmacro-backtrace-limit=0","-ferror-limit=1000","-x","c++-header","D:\\proejcts\\qtYTDownalde\\YtDownloaderQt\\videolistelement.h"],"directory":"D:/proejcts/qtYTDownalde/YtDownloaderQt/build/Desktop_Qt_6_6_2_MinGW_64_bit-Debug/.qtc_clangd","file":"D:/proejcts/qtYTDownalde/YtDownloaderQt/videolistelement.h"},{"arguments":["clang","-Wno-documentation-unknown-command","-Wno-unknown-warning-option","-Wno-unknown-pragmas","-nostdinc","-nostdinc++","-g","-std=gnu++1z","-Wall","-Wextra","-Wextra","-fexceptions","-mthreads","-fsyntax-only","-m64","--target=x86_64-w64-mingw32","-DUNICODE","-D_UNICODE","-DWIN32","-DMINGW_HAS_SECURE_API","-DQT_QML_DEBUG","-DQT_QUICKCONTROLS2_LIB","-DQT_QUICK_LIB","-DQT_OPENGL_LIB","-DQT_WIDGETS_LIB","-DQT_GUI_LIB","-DQT_QMLMODELS_LIB","-DQT_QML_LIB","-DQT_QMLINTEGRATION_LIB","-DQT_NETWORK_LIB","-DQT_CORE_LIB","-DQT_NEEDS_QMAIN","-DQ_CREATOR_RUN","-DQT_ANNOTATE_FUNCTION(x)=__attribute__((annotate(#x)))","-ID:\\pliki\\qt\\Tools\\Qt Creator 13.0.0-rc1\\share\\qtcreator\\cplusplus\\wrappedMingwHeaders","-ID:\\pliki\\qt\\Tools\\Qt Creator 13.0.0-rc1\\share\\qtcreator\\cplusplus\\wrappedQtHeaders","-ID:\\pliki\\qt\\Tools\\Qt Creator 13.0.0-rc1\\share\\qtcreator\\cplusplus\\wrappedQtHeaders\\QtCore","-ID:\\proejcts\\qtYTDownalde\\YtDownloaderQt","-ID:\\proejcts\\qtYTDownalde\\YtDownloaderQt\\YtDlpWrapper","-ID:\\pliki\\qt\\6.6.2\\mingw_64\\include","-ID:\\pliki\\qt\\6.6.2\\mingw_64\\include\\QtQuickControls2","-ID:\\pliki\\qt\\6.6.2\\mingw_64\\include\\QtQuick","-ID:\\pliki\\qt\\6.6.2\\mingw_64\\include\\QtOpenGL","-ID:\\pliki\\qt\\6.6.2\\mingw_64\\include\\QtWidgets","-ID:\\pliki\\qt\\6.6.2\\mingw_64\\include\\QtGui","-ID:\\pliki\\qt\\6.6.2\\mingw_64\\include\\QtQmlModels","-ID:\\pliki\\qt\\6.6.2\\mingw_64\\include\\QtQml","-ID:\\pliki\\qt\\6.6.2\\mingw_64\\include\\QtQmlIntegration","-ID:\\pliki\\qt\\6.6.2\\mingw_64\\include\\QtNetwork","-ID:\\pliki\\qt\\6.6.2\\mingw_64\\include\\QtCore","-ID:\\proejcts\\qtYTDownalde\\YtDownloaderQt\\build\\Desktop_Qt_6_6_2_MinGW_64_bit-Debug\\debug","-ID:\\proejcts\\qtYTDownalde\\YtDownloaderQt\\build\\Desktop_Qt_6_6_2_MinGW_64_bit-Debug","-ID:\\pliki\\qt\\6.6.2\\mingw_64\\mkspecs\\win32-g++","-isystem","D:\\pliki\\qt\\Tools\\mingw1120_64\\lib\\gcc\\x86_64-w64-mingw32\\11.2.0\\include\\c++","-isystem","D:\\pliki\\qt\\Tools\\mingw1120_64\\lib\\gcc\\x86_64-w64-mingw32\\11.2.0\\include\\c++\\x86_64-w64-mingw32","-isystem","D:\\pliki\\qt\\Tools\\mingw1120_64\\lib\\gcc\\x86_64-w64-mingw32\\11.2.0\\include\\c++\\backward","-isystem","D:\\pliki\\qt\\Tools\\Qt Creator 13.0.0-rc1\\bin\\clang\\lib\\clang\\17\\include","-isystem","D:\\pliki\\qt\\Tools\\mingw1120_64\\x86_64-w64-mingw32\\include","-fmessage-length=0","-fdiagnostics-show-note-include-stack","-fretain-comments-from-system-headers","-fmacro-backtrace-limit=0","-ferror-limit=1000","-x","c++-header","D:\\proejcts\\qtYTDownalde\\YtDownloaderQt\\ytdownloader.h"],"directory":"D:/proejcts/qtYTDownalde/YtDownloaderQt/build/Desktop_Qt_6_6_2_MinGW_64_bit-Debug/.qtc_clangd","file":"D:/proejcts/qtYTDownalde/YtDownloaderQt/ytdownloader.h"},{"arguments":["clang","-Wno-documentation-unknown-command","-Wno-unknown-warning-option","-Wno-unknown-pragmas","-nostdinc","-nostdinc++","-g","-std=gnu++1z","-Wall","-Wextra","-Wextra","-fexceptions","-mthreads","-fsyntax-only","-m64","--target=x86_64-w64-mingw32","-DUNICODE","-D_UNICODE","-DWIN32","-DMINGW_HAS_SECURE_API","-DQT_QML_DEBUG","-DQT_QUICKCONTROLS2_LIB","-DQT_QUICK_LIB","-DQT_OPENGL_LIB","-DQT_WIDGETS_LIB","-DQT_GUI_LIB","-DQT_QMLMODELS_LIB","-DQT_QML_LIB","-DQT_QMLINTEGRATION_LIB","-DQT_NETWORK_LIB","-DQT_CORE_LIB","-DQT_NEEDS_QMAIN","-DQ_CREATOR_RUN","-DQT_ANNOTATE_FUNCTION(x)=__attribute__((annotate(#x)))","-ID:\\pliki\\qt\\Tools\\Qt Creator 13.0.0-rc1\\share\\qtcreator\\cplusplus\\wrappedMingwHeaders","-ID:\\pliki\\qt\\Tools\\Qt Creator 13.0.0-rc1\\share\\qtcreator\\cplusplus\\wrappedQtHeaders","-ID:\\pliki\\qt\\Tools\\Qt Creator 13.0.0-rc1\\share\\qtcreator\\cplusplus\\wrappedQtHeaders\\QtCore","-ID:\\proejcts\\qtYTDownalde\\YtDownloaderQt","-ID:\\proejcts\\qtYTDownalde\\YtDownloaderQt\\YtDlpWrapper","-ID:\\pliki\\qt\\6.6.2\\mingw_64\\include","-ID:\\pliki\\qt\\6.6.2\\mingw_64\\include\\QtQuickControls2","-ID:\\pliki\\qt\\6.6.2\\mingw_64\\include\\QtQuick","-ID:\\pliki\\qt\\6.6.2\\mingw_64\\include\\QtOpenGL","-ID:\\pliki\\qt\\6.6.2\\mingw_64\\include\\QtWidgets","-ID:\\pliki\\qt\\6.6.2\\mingw_64\\include\\QtGui","-ID:\\pliki\\qt\\6.6.2\\mingw_64\\include\\QtQmlModels","-ID:\\pliki\\qt\\6.6.2\\mingw_64\\include\\QtQml","-ID:\\pliki\\qt\\6.6.2\\mingw_64\\include\\QtQmlIntegration","-ID:\\pliki\\qt\\6.6.2\\mingw_64\\include\\QtNetwork","-ID:\\pliki\\qt\\6.6.2\\mingw_64\\include\\QtCore","-ID:\\proejcts\\qtYTDownalde\\YtDownloaderQt\\build\\Desktop_Qt_6_6_2_MinGW_64_bit-Debug\\debug","-ID:\\proejcts\\qtYTDownalde\\YtDownloaderQt\\build\\Desktop_Qt_6_6_2_MinGW_64_bit-Debug","-ID:\\pliki\\qt\\6.6.2\\mingw_64\\mkspecs\\win32-g++","-isystem","D:\\pliki\\qt\\Tools\\mingw1120_64\\lib\\gcc\\x86_64-w64-mingw32\\11.2.0\\include\\c++","-isystem","D:\\pliki\\qt\\Tools\\mingw1120_64\\lib\\gcc\\x86_64-w64-mingw32\\11.2.0\\include\\c++\\x86_64-w64-mingw32","-isystem","D:\\pliki\\qt\\Tools\\mingw1120_64\\lib\\gcc\\x86_64-w64-mingw32\\11.2.0\\include\\c++\\backward","-isystem","D:\\pliki\\qt\\Tools\\Qt Creator 13.0.0-rc1\\bin\\clang\\lib\\clang\\17\\include","-isystem","D:\\pliki\\qt\\Tools\\mingw1120_64\\x86_64-w64-mingw32\\include","-fmessage-length=0","-fdiagnostics-show-note-include-stack","-fretain-comments-from-system-headers","-fmacro-backtrace-limit=0","-ferror-limit=1000","-x","c++-header","D:\\proejcts\\qtYTDownalde\\YtDownloaderQt\\build\\Desktop_Qt_6_6_2_MinGW_64_bit-Debug\\ui_videolistelement.h"],"directory":"D:/proejcts/qtYTDownalde/YtDownloaderQt/build/Desktop_Qt_6_6_2_MinGW_64_bit-Debug/.qtc_clangd","file":"D:/proejcts/qtYTDownalde/YtDownloaderQt/build/Desktop_Qt_6_6_2_MinGW_64_bit-Debug/ui_videolistelement.h"},{"arguments":["clang","-Wno-documentation-unknown-command","-Wno-unknown-warning-option","-Wno-unknown-pragmas","-nostdinc","-nostdinc++","-g","-std=gnu++1z","-Wall","-Wextra","-Wextra","-fexceptions","-mthreads","-fsyntax-only","-m64","--target=x86_64-w64-mingw32","-DUNICODE","-D_UNICODE","-DWIN32","-DMINGW_HAS_SECURE_API","-DQT_QML_DEBUG","-DQT_QUICKCONTROLS2_LIB","-DQT_QUICK_LIB","-DQT_OPENGL_LIB","-DQT_WIDGETS_LIB","-DQT_GUI_LIB","-DQT_QMLMODELS_LIB","-DQT_QML_LIB","-DQT_QMLINTEGRATION_LIB","-DQT_NETWORK_LIB","-DQT_CORE_LIB","-DQT_NEEDS_QMAIN","-DQ_CREATOR_RUN","-DQT_ANNOTATE_FUNCTION(x)=__attribute__((annotate(#x)))","-ID:\\pliki\\qt\\Tools\\Qt Creator 13.0.0-rc1\\share\\qtcreator\\cplusplus\\wrappedMingwHeaders","-ID:\\pliki\\qt\\Tools\\Qt Creator 13.0.0-rc1\\share\\qtcreator\\cplusplus\\wrappedQtHeaders","-ID:\\pliki\\qt\\Tools\\Qt Creator 13.0.0-rc1\\share\\qtcreator\\cplusplus\\wrappedQtHeaders\\QtCore","-ID:\\proejcts\\qtYTDownalde\\YtDownloaderQt","-ID:\\proejcts\\qtYTDownalde\\YtDownloaderQt\\YtDlpWrapper","-ID:\\pliki\\qt\\6.6.2\\mingw_64\\include","-ID:\\pliki\\qt\\6.6.2\\mingw_64\\include\\QtQuickControls2","-ID:\\pliki\\qt\\6.6.2\\mingw_64\\include\\QtQuick","-ID:\\pliki\\qt\\6.6.2\\mingw_64\\include\\QtOpenGL","-ID:\\pliki\\qt\\6.6.2\\mingw_64\\include\\QtWidgets","-ID:\\pliki\\qt\\6.6.2\\mingw_64\\include\\QtGui","-ID:\\pliki\\qt\\6.6.2\\mingw_64\\include\\QtQmlModels","-ID:\\pliki\\qt\\6.6.2\\mingw_64\\include\\QtQml","-ID:\\pliki\\qt\\6.6.2\\mingw_64\\include\\QtQmlIntegration","-ID:\\pliki\\qt\\6.6.2\\mingw_64\\include\\QtNetwork","-ID:\\pliki\\qt\\6.6.2\\mingw_64\\include\\QtCore","-ID:\\proejcts\\qtYTDownalde\\YtDownloaderQt\\build\\Desktop_Qt_6_6_2_MinGW_64_bit-Debug\\debug","-ID:\\proejcts\\qtYTDownalde\\YtDownloaderQt\\build\\Desktop_Qt_6_6_2_MinGW_64_bit-Debug","-ID:\\pliki\\qt\\6.6.2\\mingw_64\\mkspecs\\win32-g++","-isystem","D:\\pliki\\qt\\Tools\\mingw1120_64\\lib\\gcc\\x86_64-w64-mingw32\\11.2.0\\include\\c++","-isystem","D:\\pliki\\qt\\Tools\\mingw1120_64\\lib\\gcc\\x86_64-w64-mingw32\\11.2.0\\include\\c++\\x86_64-w64-mingw32","-isystem","D:\\pliki\\qt\\Tools\\mingw1120_64\\lib\\gcc\\x86_64-w64-mingw32\\11.2.0\\include\\c++\\backward","-isystem","D:\\pliki\\qt\\Tools\\Qt Creator 13.0.0-rc1\\bin\\clang\\lib\\clang\\17\\include","-isystem","D:\\pliki\\qt\\Tools\\mingw1120_64\\x86_64-w64-mingw32\\include","-fmessage-length=0","-fdiagnostics-show-note-include-stack","-fretain-comments-from-system-headers","-fmacro-backtrace-limit=0","-ferror-limit=1000","-x","c++-header","D:\\proejcts\\qtYTDownalde\\YtDownloaderQt\\build\\Desktop_Qt_6_6_2_MinGW_64_bit-Debug\\ui_ytdownloader.h"],"directory":"D:/proejcts/qtYTDownalde/YtDownloaderQt/build/Desktop_Qt_6_6_2_MinGW_64_bit-Debug/.qtc_clangd","file":"D:/proejcts/qtYTDownalde/YtDownloaderQt/build/Desktop_Qt_6_6_2_MinGW_64_bit-Debug/ui_ytdownloader.h"}]